{
    "authors": {
        "TuyaInc": "https://developer.tuya.com/"
    },
    "cocoapods_version": ">= 1.10",
    "dependencies": {
        "TYEncryptImage": [],
        "TYFoundationKit": [],
        "TYKVStorageLibrary": [],
        "TYModuleManager": [],
        "TYModuleServices": [],
        "TYOEMConfig": [],
        "TYSmartBusinessLibrary": [],
        "TYSmartEventPredefined": [],
        "TYSmartUIConfigServices": [],
        "TYSmartUserCenterDefaultUISkin": [],
        "TYTemplateSkeleton": [],
        "TYUIKit": [],
        "TYUrlPredefined": [],
        "TuyaSmartBaseKit": [],
        "TuyaSmartDeviceKit": [],
        "TuyaSmartUtil": []
    },
    "frameworks": [
        "UIKit",
        "Foundation",
        "StoreKit"
    ],
    "homepage": "https://github.com/tuya",
    "license": "none",
    "name": "TYSettingsModule",
    "platforms": {
        "ios": "9.0"
    },
    "pod_target_xcconfig": {
        "EXCLUDED_ARCHS[sdk=iphonesimulator*]": "arm64",
        "EXCLUDED_ARCHS[sdk=watchsimulator*]": "x86_64 arm64"
    },
    "prefix_header_contents": "#import <TYLogMacro/TYLogMacro.h>\n\n#undef TYLogDebug\n#define TYLogDebug(...) TYLogger(0, @\"TYSettingsModule\", ##__VA_ARGS__)\n\n#undef TYLogInfo\n#define TYLogInfo(...)  TYLogger(1,  @\"TYSettingsModule\", ##__VA_ARGS__)\n\n#undef TYLogWarn\n#define TYLogWarn(...)  TYLogger(2,  @\"TYSettingsModule\", ##__VA_ARGS__)\n\n#undef TYLogError\n#define TYLogError(...) TYLogger(3, @\"TYSettingsModule\", ##__VA_ARGS__)",
    "prefix_header_file": "TYSettingsModule/Classes/PrefixHeader.pch",
    "resources": [
        "TYSettingsModule/Assets/*.{png,xib,plist,xcassets,bundle}"
    ],
    "source": {
        "http": "https://airtake-public-data-1254153901.cos.ap-shanghai.myqcloud.com/smart/app/package/pods/ios/TYSettingsModule-3.34.5-feature-3.34.5fix.3.zip",
        "type": "zip"
    },
    "summary": "涂鸦组件模板",
    "user_target_xcconfig": {
        "EXCLUDED_ARCHS[sdk=iphonesimulator*]": "arm64",
        "EXCLUDED_ARCHS[sdk=watchsimulator*]": "x86_64 arm64"
    },
    "vendored_frameworks": [
        "TYSettingsModule.xcframework"
    ],
    "version": "3.34.5-feature-3.34.5fix.3"
}