{
    "authors": {
        "TuyaInc": "https://developer.tuya.com/"
    },
    "cocoapods_version": ">= 1.10",
    "dependencies": {
        "IQKeyboardManager": [],
        "TYEncryptImage": [],
        "TYFoundationKit": [],
        "TYKVStorageLibrary": [],
        "TYModuleManager": [],
        "TYModuleServices": [],
        "TYPopupViewController": [],
        "TYSmartBusinessLibrary": [],
        "TYSmartEventPredefined": [],
        "TYSmartEventPredefined_Public": [],
        "TYSmartFamilyBizKit": [],
        "TYSmartUIConfigServices": [],
        "TYTabPagingView": [],
        "TYUIKit": [],
        "TYUrlPredefined": [],
        "TYUrlPredefinedExternal": [],
        "TuyaSmartBaseKit": [],
        "TuyaSmartDeviceKit": []
    },
    "frameworks": [
        "UIKit",
        "Foundation",
        "MapKit"
    ],
    "homepage": "https://github.com/tuya",
    "license": "none",
    "name": "TYSmartFamilyDefaultUISkin",
    "platforms": {
        "ios": "9.0"
    },
    "pod_target_xcconfig": {
        "TUYA_PRIVACY_USAGE_DESCRIPTION": "NSLocationAlwaysAndWhenInUseUsageDescription"
    },
    "prefix_header_contents": "#import <TYLogMacro/TYLogMacro.h>\n\n#undef TYLogDebug\n#define TYLogDebug(...) TYLogger(0, @\"TYSmartFamilyDefaultUISkin\", ##__VA_ARGS__)\n\n#undef TYLogInfo\n#define TYLogInfo(...)  TYLogger(1,  @\"TYSmartFamilyDefaultUISkin\", ##__VA_ARGS__)\n\n#undef TYLogWarn\n#define TYLogWarn(...)  TYLogger(2,  @\"TYSmartFamilyDefaultUISkin\", ##__VA_ARGS__)\n\n#undef TYLogError\n#define TYLogError(...) TYLogger(3, @\"TYSmartFamilyDefaultUISkin\", ##__VA_ARGS__)",
    "resource_bundles": {
        "TYSmartFamilyDefaultUISkin": "Build/TYSmartFamilyDefaultUISkin.xcframework/ios-arm64_armv7/TYSmartFamilyDefaultUISkin.framework/CustomResources/Bundles/TYSmartFamilyDefaultUISkin.bundle/**"
    },
    "source": {
        "http": "https://airtake-public-data-1254153901.cos.ap-shanghai.myqcloud.com/smart/app/package/pods/ios/TYSmartFamilyDefaultUISkin-2.11.3-tybizbundle-3.32.5.2.zip",
        "type": "zip"
    },
    "summary": "涂鸦家庭模块默认皮肤",
    "vendored_frameworks": [
        "Build/TYSmartFamilyDefaultUISkin.xcframework"
    ],
    "version": "2.11.3-tybizbundle-3.32.5.2"
}
