{
    "authors": {
        "TuyaInc": "https://developer.tuya.com/"
    },
    "dependencies": {
        "TYLogMacro": [],
        "TYPanelContext": [],
        "TYPanelSweeperUtil": [],
        "TYReactNative": []
    },
    "description": "TYRCTVisionMapManager",
    "homepage": "https://github.com/tuya",
    "license": "none",
    "name": "TYRCTVisionMapManager",
    "platforms": {
        "ios": "9.0"
    },
    "prefix_header_contents": "#import <TYLogMacro/TYLogMacro.h>\n\n#undef TYLogDebug\n#define TYLogDebug(...) TYLogger(0, @\"TYRCTVisionMapManager\", ##__VA_ARGS__)\n\n#undef TYLogInfo\n#define TYLogInfo(...)  TYLogger(1,  @\"TYRCTVisionMapManager\", ##__VA_ARGS__)\n\n#undef TYLogWarn\n#define TYLogWarn(...)  TYLogger(2,  @\"TYRCTVisionMapManager\", ##__VA_ARGS__)\n\n#undef TYLogError\n#define TYLogError(...) TYLogger(3, @\"TYRCTVisionMapManager\", ##__VA_ARGS__)",
    "source": {
        "http": "https://images.tuyacn.com/smart/app/package/pods/ios/TYRCTVisionMapManager-1.0.20.zip",
        "type": "zip"
    },
    "summary": "TYRCTVisionMapManager",
    "vendored_libraries": "TYRCTVisionMapManager-1.0.20/libTYRCTVisionMapManager.a",
    "version": "1.0.20"
}